logmuse/__init__.py
logmuse/_version.py
logmuse/est.py
logmuse-0.2.7.dist-info/LICENSE.txt
logmuse-0.2.7.dist-info/METADATA
logmuse-0.2.7.dist-info/WHEEL
logmuse-0.2.7.dist-info/top_level.txt
logmuse-0.2.7.dist-info/RECORD
