Metadata-Version: 2.1
Name: logmuse
Version: 0.2.7
Summary: Logging setup
Home-page: https://github.com/databio/logmuse/
Author: Vince Reuter, Nathan Sheffield
License: BSD-2-Clause
Keywords: logging,workflow,logger,logs
Platform: UNKNOWN
Classifier: Development Status :: 4 - Beta
Classifier: License :: OSI Approved :: BSD License
Classifier: Programming Language :: Python :: 2.7
Classifier: Programming Language :: Python :: 3.5
Classifier: Programming Language :: Python :: 3.6
